jtos/__init__.py
jtos/jtos.py
JTOS-0.8.2.dist-info/LICENSE.md
JTOS-0.8.2.dist-info/METADATA
JTOS-0.8.2.dist-info/WHEEL
JTOS-0.8.2.dist-info/top_level.txt
JTOS-0.8.2.dist-info/RECORD
