Metadata-Version: 2.1
Name: JTOS
Version: 0.8.2
Summary: A JSON query to SQL parser loosely based on the Loopback Query Language
Home-page: https://github.com/encima/jtos
Author: encima
Author-email: encima@gmail.com
License: UNKNOWN
Platform: UNKNOWN
Classifier: Development Status :: 3 - Alpha
Classifier: Intended Audience :: Developers
Classifier: Topic :: Software Development
Classifier: Topic :: Database
Classifier: License :: OSI Approved :: MIT License
Classifier: Programming Language :: Python :: 2
Classifier: Programming Language :: Python :: 2.6
Classifier: Programming Language :: Python :: 2.7
Classifier: Programming Language :: Python :: 3
